README.rst
setup.py
dashtable/__init__.py
dashtable/html2md.py
dashtable/html2rst.py
dashtable.egg-info/PKG-INFO
dashtable.egg-info/SOURCES.txt
dashtable.egg-info/dependency_links.txt
dashtable.egg-info/top_level.txt
dashtable/dashutils/__init__.py
dashtable/dashutils/add_cushions.py
dashtable/dashutils/center_line.py
dashtable/dashutils/check_span.py
dashtable/dashutils/check_table.py
dashtable/dashutils/ensure_table_strings.py
dashtable/dashutils/get_longest_line_length.py
dashtable/dashutils/get_span.py
dashtable/dashutils/get_span_char_height.py
dashtable/dashutils/get_span_char_width.py
dashtable/dashutils/get_span_column_count.py
dashtable/dashutils/get_span_row_count.py
dashtable/dashutils/make_empty_table.py
dashtable/dashutils/make_span.py
dashtable/dashutils/multis_2_mono.py
dashtable/data2md/__init__.py
dashtable/data2md/data2md.py
dashtable/data2md/get_column_width.py
dashtable/data2rst/__init__.py
dashtable/data2rst/data2rst.py
dashtable/data2rst/get_output_column_widths.py
dashtable/data2rst/get_output_row_heights.py
dashtable/data2rst/make_cell.py
dashtable/data2rst/merge_all_cells.py
dashtable/data2rst/table_cells_2_spans.py
dashtable/data2rst/cell/__init__.py
dashtable/data2rst/cell/cell.py
dashtable/data2rst/cell/center_cell_text.py
dashtable/data2rst/cell/get_longest_line_length.py
dashtable/data2rst/cell/get_merge_direction.py
dashtable/data2rst/cell/is_only.py
dashtable/data2rst/cell/merge_cells.py
dashtable/data2rst/cell/v_center_cell_text.py
dashtable/data2simplerst/__init__.py
dashtable/data2simplerst/data2simplerst.py
dashtable/data2simplerst/row_includes_spans.py
dashtable/grid2data/__init__.py
dashtable/grid2data/grid2data.py
dashtable/html2data/__init__.py
dashtable/html2data/extract_spans.py
dashtable/html2data/extract_table.py
dashtable/html2data/find_unassigned_table_cell.py
dashtable/html2data/get_html_column_count.py
dashtable/html2data/get_html_row_count.py
dashtable/html2data/headers_present.py
dashtable/html2data/html2data.py
dashtable/html2data/restructify/__init__.py
dashtable/html2data/restructify/add_links.py
dashtable/html2data/restructify/process_tag.py
