Metadata-Version: 1.1
Name: dashtable
Version: 1.4.4
Summary: A library for converting a HTML tables into ASCII tables, rowspan and colspan allowed!
Home-page: https://github.com/doakey3/DashTable
Author: doakey3 & gustavklopp
Author-email: dashtable.dmodo@spamgourmet.com
License: MIT
Download-URL: https://github.com/doakey3/DashTable/tarball/1.4.4
Platform: UNKNOWN
